yt_dlp_transript/__init__.py
yt_dlp_transript-0.1.8.dist-info/METADATA
yt_dlp_transript-0.1.8.dist-info/WHEEL
yt_dlp_transript-0.1.8.dist-info/entry_points.txt
yt_dlp_transript-0.1.8.dist-info/top_level.txt
yt_dlp_transript-0.1.8.dist-info/RECORD
