Metadata-Version: 2.1
Name: yt-dlp-transript
Version: 0.1.8
Summary: Handy yt-dlp wrapper to download Youtube videos transcripts
Author-email: Alexander Ryabov <alex.ryabov@gmail.com>
Project-URL: Homepage, https://github.com/haron/yt-dlp-transript
Project-URL: Issues, https://github.com/haron/yt-dlp-transript/issues
Classifier: Programming Language :: Python :: 3
Classifier: Operating System :: OS Independent
Requires-Python: >=3.12
Requires-Dist: yt-dlp
Requires-Dist: ConfigArgParse
Requires-Dist: srt
